{"poule":"D2J","stand":[{"stand":"1","team":"Aspasia DS 1","wedstrijden":"13","punten":"60"},{"stand":"2","team":"VVV Delta DS 2","wedstrijden":"13","punten":"55"},{"stand":"3","team":"SKC DS 3","wedstrijden":"13","punten":"47"},{"stand":"4","team":"Inter Rijswijk DS 5","wedstrijden":"15","punten":"31"},{"stand":"5","team":"Punch DS 4","wedstrijden":"12","punten":"29"},{"stand":"6","team":"Leython DC DS 5","wedstrijden":"13","punten":"29"},{"stand":"7","team":"Kalinko DS 6","wedstrijden":"11","punten":"28"},{"stand":"8","team":"VOLEVO DS 5","wedstrijden":"10","punten":"26"},{"stand":"9","team":"Velo\/Volevo DS 3","wedstrijden":"12","punten":"23"},{"stand":"10","team":"PQV Pijl Solutions DS 1","wedstrijden":"13","punten":"22"},{"stand":"11","team":"Sovicos DS 3","wedstrijden":"12","punten":"17"},{"stand":"12","team":"Kratos '08 DS 4","wedstrijden":"13","punten":"12"}],"uitslagen":[{"teams":"Velo\/Volevo DS 3 - SKC DS 3","setsVoor":2,"setsTegen":3,"setstanden":"23-25, 25-19, 18-25, 25-19, 6-15"},{"teams":"VOLEVO DS 5 - SKC DS 3","setsVoor":2,"setsTegen":3,"setstanden":"30-28, 19-25, 22-25, 25-20, 10-15"},{"teams":"SKC DS 3 - VVV Delta DS 2","setsVoor":2,"setsTegen":3,"setstanden":"25-19, 16-25, 25-19, 19-25, 14-16"}],"programma":[{"tijd":"19:30","teams":"SKC DS 3 - Leython DC DS 5","dag":"Vrijdag 31 Januari","locatie":"Universitair SC, Einsteinweg 6, 2333CC LEIDEN"},{"tijd":"21:30","teams":"Kratos '08 DS 4 - SKC DS 3","dag":"Vrijdag 7 Februari","locatie":"Tanthof, Henk Van Riessenlaan 5, 2626AB DELFT"},{"tijd":"19:30","teams":"SKC DS 3 - PQV Pijl Solutions DS 1","dag":"Vrijdag 14 Februari","locatie":"Universitair SC, Einsteinweg 6, 2333CC LEIDEN"}]}