{"poule":"H4G","stand":[{"stand":"1","team":"Castellum HS 3","wedstrijden":"12","punten":"53"},{"stand":"2","team":"Servylo HS 3","wedstrijden":"11","punten":"49"},{"stand":"3","team":"Scarabee HS 3","wedstrijden":"11","punten":"35"},{"stand":"4","team":"GGV HS 2","wedstrijden":"10","punten":"30"},{"stand":"5","team":"VCS HS 4","wedstrijden":"10","punten":"24"},{"stand":"6","team":"In Up Go HS 2","wedstrijden":"11","punten":"22"},{"stand":"7","team":"GGV HS 3","wedstrijden":"13","punten":"20"},{"stand":"8","team":"SKC HS 7","wedstrijden":"12","punten":"19"},{"stand":"9","team":"SKC HS 6","wedstrijden":"9","punten":"12"},{"stand":"10","team":"SKC HS 9","wedstrijden":"11","punten":"11"}],"uitslagen":[{"teams":"SKC HS 6 - Castellum HS 3","setsVoor":0,"setsTegen":4,"setstanden":"15-25, 8-25, 15-25, 15-25"},{"teams":"SKC HS 6 - GGV HS 3","setsVoor":2,"setsTegen":3,"setstanden":"25-18, 12-25, 21-25, 25-23, 7-15"},{"teams":"SKC HS 9 - SKC HS 6","setsVoor":3,"setsTegen":2,"setstanden":"14-25, 25-15, 25-17, 17-25, 15-13"}],"programma":[{"tijd":"19:30","teams":"Servylo HS 3 - SKC HS 6","dag":"Vrijdag 31 Januari","locatie":"De Mammoet, Calslaan 101, 2804RT GOUDA"},{"tijd":"19:30","teams":"SKC HS 6 - SKC HS 7","dag":"Vrijdag 7 Februari","locatie":"Universitair SC, Einsteinweg 6, 2333CC LEIDEN"},{"tijd":"14:30","teams":"GGV HS 2 - SKC HS 6","dag":"Zaterdag 15 Februari","locatie":"De Vliethorst, Burg Van Der Haarplein 9, 2251CT VOORSCHOTEN"}]}